citsci_notebook_core_pipeline/__init__.py
citsci_notebook_core_pipeline/rubin_citsci_core_pipeline.py
citsci_notebook_core_pipeline-0.1.1.dist-info/LICENSE
citsci_notebook_core_pipeline-0.1.1.dist-info/METADATA
citsci_notebook_core_pipeline-0.1.1.dist-info/WHEEL
citsci_notebook_core_pipeline-0.1.1.dist-info/top_level.txt
citsci_notebook_core_pipeline-0.1.1.dist-info/RECORD
