Metadata-Version: 2.1
Name: citsci-notebook-core-pipeline
Version: 0.1.1
License-File: LICENSE
Requires-Dist: panoptes-client
Requires-Dist: google.cloud.storage
